mseep_python_a2a-0.5.9.dist-info/licenses/LICENSE
python_a2a/__init__.py
python_a2a/cli.py
python_a2a/client.py
python_a2a/exceptions.py
python_a2a/py.typed
python_a2a/agent_flow/__init__.py
python_a2a/agent_flow/cli.py
python_a2a/agent_flow/engine/__init__.py
python_a2a/agent_flow/engine/executor.py
python_a2a/agent_flow/examples/__init__.py
python_a2a/agent_flow/models/__init__.py
python_a2a/agent_flow/models/agent.py
python_a2a/agent_flow/models/tool.py
python_a2a/agent_flow/models/workflow.py
python_a2a/agent_flow/server/__init__.py
python_a2a/agent_flow/server/agent_api.py
python_a2a/agent_flow/server/api.py
python_a2a/agent_flow/server/web.py
python_a2a/agent_flow/server/static/__init__.py
python_a2a/agent_flow/server/static/css/__init__.py
python_a2a/agent_flow/server/static/images/__init__.py
python_a2a/agent_flow/server/static/js/__init__.py
python_a2a/agent_flow/server/templates/__init__.py
python_a2a/agent_flow/storage/__init__.py
python_a2a/agent_flow/storage/workflow_storage.py
python_a2a/agent_flow/utils/__init__.py
python_a2a/agent_flow/utils/agent_manager.py
python_a2a/client/__init__.py
python_a2a/client/base.py
python_a2a/client/http.py
python_a2a/client/network.py
python_a2a/client/router.py
python_a2a/client/streaming.py
python_a2a/client/llm/__init__.py
python_a2a/client/llm/anthropic.py
python_a2a/client/llm/bedrock.py
python_a2a/client/llm/ollama.py
python_a2a/client/llm/openai.py
python_a2a/discovery/__init__.py
python_a2a/discovery/client.py
python_a2a/discovery/registry.py
python_a2a/discovery/server.py
python_a2a/docs/__init__.py
python_a2a/docs/openai.py
python_a2a/langchain/__init__.py
python_a2a/langchain/a2a.py
python_a2a/langchain/exceptions.py
python_a2a/langchain/mcp.py
python_a2a/mcp/__init__.py
python_a2a/mcp/agent.py
python_a2a/mcp/client.py
python_a2a/mcp/client_transport.py
python_a2a/mcp/clients.py
python_a2a/mcp/connection.py
python_a2a/mcp/fastmcp.py
python_a2a/mcp/integration.py
python_a2a/mcp/protocol.py
python_a2a/mcp/proxy.py
python_a2a/mcp/server.py
mseep_python_a2a-0.5.9.dist-info/METADATA
mseep_python_a2a-0.5.9.dist-info/WHEEL
mseep_python_a2a-0.5.9.dist-info/top_level.txt
mseep_python_a2a-0.5.9.dist-info/RECORD
