Metadata-Version: 2.4
Name: mseep-python-a2a
Version: 0.5.9
Summary: A comprehensive Python library for Google's Agent-to-Agent (A2A) protocol
Home-page: https://github.com/mseep
Author: mseep
Author-email: support@skydeck.ai
Maintainer: mseep
Maintainer-email: support@skydeck.ai
Keywords: mseep,a2a,agent,ai,llm,interoperability,google,protocol,chatbot,openai,anthropic,claude,huggingface,mcp,model-context-protocol,aws-bedrock,langchain
Classifier: Programming Language :: Python :: 3
Classifier: License :: OSI Approved :: MIT License
Classifier: Operating System :: OS Independent
Requires-Python: >=3.6
License-File: LICENSE
Requires-Dist: requests>=2.25.0
Requires-Dist: flask>=2.0.0
Requires-Dist: aiohttp>=3.8.0
Requires-Dist: openai>=1.0.0
Requires-Dist: anthropic>=0.3.0
Requires-Dist: boto3>=1.26.0
Requires-Dist: botocore>=1.29.0
Requires-Dist: httpx>=0.23.0
Requires-Dist: fastapi>=0.95.0
Requires-Dist: uvicorn>=0.21.0
Requires-Dist: pydantic>=1.10.7
Requires-Dist: langchain>=0.1.0
Dynamic: author
Dynamic: author-email
Dynamic: classifier
Dynamic: description
Dynamic: description-content-type
Dynamic: home-page
Dynamic: keywords
Dynamic: license-file
Dynamic: maintainer
Dynamic: maintainer-email
Dynamic: requires-dist
Dynamic: requires-python
Dynamic: summary
